mvm_smart_meter/__init__.py
mvm_smart_meter/smart_meter.py
mvm_smart_metering-0.0.16.dist-info/METADATA
mvm_smart_metering-0.0.16.dist-info/WHEEL
mvm_smart_metering-0.0.16.dist-info/RECORD
