Metadata-Version: 2.1
Name: mvm-smart-metering
Version: 0.0.16
Summary: Script for scraping mvm smart meter data
Author: ktomi96
Author-email: kokai.tamas.96@gmail.com
Requires-Python: >=3.11,<4.0
Classifier: Programming Language :: Python :: 3
Classifier: Programming Language :: Python :: 3.11
Requires-Dist: beautifulsoup4 (>=4.11.1,<5.0.0)
Requires-Dist: pandas (==2.0.2)
Requires-Dist: python-dotenv (==1.0.0)
Requires-Dist: requestium (==0.2.1)
Requires-Dist: requests (>=2.28.2,<3.0.0)
Requires-Dist: webdriver-manager (>=3.8.5,<4.0.0)
